README.md
setup.py
baseplots/Generalplot.py
baseplots/Plot1d.py
baseplots/Plot2d.py
baseplots/__init__.py
baseplots.egg-info/PKG-INFO
baseplots.egg-info/SOURCES.txt
baseplots.egg-info/dependency_links.txt
baseplots.egg-info/not-zip-safe
baseplots.egg-info/top_level.txt