Metadata-Version: 1.0
Name: baseplots
Version: 0.1
Summary: standardized plots from matplotlib and seaborn
Home-page: UNKNOWN
Author: UNKNOWN
Author-email: UNKNOWN
License: UNKNOWN
Platform: UNKNOWN
